chaosprometheus/__init__.py
chaosprometheus/metrics.py
chaosprometheus/probes.py
chaostoolkit_prometheus-0.6.0.dist-info/LICENSE
chaostoolkit_prometheus-0.6.0.dist-info/METADATA
chaostoolkit_prometheus-0.6.0.dist-info/WHEEL
chaostoolkit_prometheus-0.6.0.dist-info/top_level.txt
chaostoolkit_prometheus-0.6.0.dist-info/RECORD
