Metadata-Version: 2.1
Name: chaostoolkit-prometheus
Version: 0.6.0
Summary: Chaos Toolkit extension querying/sending metrics to Prometheus
Home-page: https://chaostoolkit.org
Author: Chaos Toolkit
Author-email: contact@chaostoolkit.org
License: Apache License Version 2.0
Project-URL: Docs: RTD, https://chaostoolkit.org
Project-URL: CI: GitHub, https://github.com/chaostoolkit-incubator/chaostoolkit-prometheus/actions
Project-URL: GitHub: issues, https://github.com/chaostoolkit-incubator/chaostoolkit-prometheus/issues
Project-URL: GitHub: repo, https://github.com/chaostoolkit-incubator/chaostoolkit-prometheus
Platform: any
Classifier: Development Status :: 5 - Production/Stable
Classifier: Intended Audience :: Developers
Classifier: License :: Freely Distributable
Classifier: License :: OSI Approved :: Apache Software License
Classifier: Operating System :: OS Independent
Classifier: Programming Language :: Python
Classifier: Programming Language :: Python :: 3
Classifier: Programming Language :: Python :: 3.7
Classifier: Programming Language :: Python :: 3.8
Classifier: Programming Language :: Python :: 3.9
Classifier: Programming Language :: Python :: 3.10
Classifier: Programming Language :: Python :: Implementation
Classifier: Programming Language :: Python :: Implementation :: CPython
Requires-Python: >=3.7
License-File: LICENSE
Requires-Dist: chaostoolkit-lib ~=1.27
Requires-Dist: requests
Requires-Dist: dateparser
Requires-Dist: maya
Requires-Dist: prometheus-client
